{
  "MathOvercome": [
    {
      "PutRequest": {
        "Item": {
          "pk": {
            "S": "PROBLEM#19"
          },
          "sk": {
            "S": "CHOICE#76"
          },
          "id": {
            "N": "76"
          },
          "problem_id": {
            "N": "19"
          },
          "choice_text": {
            "S": "6"
          },
          "is_correct": {
            "BOOL": true
          }
        }
      }
    },
    {
      "PutRequest": {
        "Item": {
          "pk": {
            "S": "PROBLEM#20"
          },
          "sk": {
            "S": "CHOICE#77"
          },
          "id": {
            "N": "77"
          },
          "problem_id": {
            "N": "20"
          },
          "choice_text": {
            "S": "12"
          },
          "is_correct": {
            "BOOL": false
          }
        }
      }
    },
    {
      "PutRequest": {
        "Item": {
          "pk": {
            "S": "PROBLEM#20"
          },
          "sk": {
            "S": "CHOICE#78"
          },
          "id": {
            "N": "78"
          },
          "problem_id": {
            "N": "20"
          },
          "choice_text": {
            "S": "3"
          },
          "is_correct": {
            "BOOL": false
          }
        }
      }
    },
    {
      "PutRequest": {
        "Item": {
          "pk": {
            "S": "PROBLEM#20"
          },
          "sk": {
            "S": "CHOICE#79"
          },
          "id": {
            "N": "79"
          },
          "problem_id": {
            "N": "20"
          },
          "choice_text": {
            "S": "1"
          },
          "is_correct": {
            "BOOL": true
          }
        }
      }
    },
    {
      "PutRequest": {
        "Item": {
          "pk": {
            "S": "PROBLEM#20"
          },
          "sk": {
            "S": "CHOICE#80"
          },
          "id": {
            "N": "80"
          },
          "problem_id": {
            "N": "20"
          },
          "choice_text": {
            "S": "2"
          },
          "is_correct": {
            "BOOL": false
          }
        }
      }
    },
    {
      "PutRequest": {
        "Item": {
          "pk": {
            "S": "PROBLEM#21"
          },
          "sk": {
            "S": "CHOICE#81"
          },
          "id": {
            "N": "81"
          },
          "problem_id": {
            "N": "21"
          },
          "choice_text": {
            "S": "0.68"
          },
          "is_correct": {
            "BOOL": false
          }
        }
      }
    },
    {
      "PutRequest": {
        "Item": {
          "pk": {
            "S": "PROBLEM#21"
          },
          "sk": {
            "S": "CHOICE#82"
          },
          "id": {
            "N": "82"
          },
          "problem_id": {
            "N": "21"
          },
          "choice_text": {
            "S": "0.88"
          },
          "is_correct": {
            "BOOL": true
          }
        }
      }
    },
    {
      "PutRequest": {
        "Item": {
          "pk": {
            "S": "PROBLEM#21"
          },
          "sk": {
            "S": "CHOICE#83"
          },
          "id": {
            "N": "83"
          },
          "problem_id": {
            "N": "21"
          },
          "choice_text": {
            "S": "0.58"
          },
          "is_correct": {
            "BOOL": false
          }
        }
      }
    },
    {
      "PutRequest": {
        "Item": {
          "pk": {
            "S": "PROBLEM#21"
          },
          "sk": {
            "S": "CHOICE#84"
          },
          "id": {
            "N": "84"
          },
          "problem_id": {
            "N": "21"
          },
          "choice_text": {
            "S": "0.45"
          },
          "is_correct": {
            "BOOL": false
          }
        }
      }
    },
    {
      "PutRequest": {
        "Item": {
          "pk": {
            "S": "PROBLEM#22"
          },
          "sk": {
            "S": "CHOICE#85"
          },
          "id": {
            "N": "85"
          },
          "problem_id": {
            "N": "22"
          },
          "choice_text": {
            "S": "増加"
          },
          "is_correct": {
            "BOOL": false
          }
        }
      }
    },
    {
      "PutRequest": {
        "Item": {
          "pk": {
            "S": "PROBLEM#22"
          },
          "sk": {
            "S": "CHOICE#86"
          },
          "id": {
            "N": "86"
          },
          "problem_id": {
            "N": "22"
          },
          "choice_text": {
            "S": "この条件では分からない"
          },
          "is_correct": {
            "BOOL": false
          }
        }
      }
    },
    {
      "PutRequest": {
        "Item": {
          "pk": {
            "S": "PROBLEM#22"
          },
          "sk": {
            "S": "CHOICE#87"
          },
          "id": {
            "N": "87"
          },
          "problem_id": {
            "N": "22"
          },
          "choice_text": {
            "S": "減少"
          },
          "is_correct": {
            "BOOL": true
          }
        }
      }
    },
    {
      "PutRequest": {
        "Item": {
          "pk": {
            "S": "PROBLEM#22"
          },
          "sk": {
            "S": "CHOICE#88"
          },
          "id": {
            "N": "88"
          },
          "problem_id": {
            "N": "22"
          },
          "choice_text": {
            "S": "一致"
          },
          "is_correct": {
            "BOOL": false
          }
        }
      }
    },
    {
      "PutRequest": {
        "Item": {
          "pk": {
            "S": "PROBLEM#23"
          },
          "sk": {
            "S": "CHOICE#89"
          },
          "id": {
            "N": "89"
          },
          "problem_id": {
            "N": "23"
          },
          "choice_text": {
            "S": "36"
          },
          "is_correct": {
            "BOOL": false
          }
        }
      }
    },
    {
      "PutRequest": {
        "Item": {
          "pk": {
            "S": "PROBLEM#23"
          },
          "sk": {
            "S": "CHOICE#90"
          },
          "id": {
            "N": "90"
          },
          "problem_id": {
            "N": "23"
          },
          "choice_text": {
            "S": "34"
          },
          "is_correct": {
            "BOOL": false
          }
        }
      }
    },
    {
      "PutRequest": {
        "Item": {
          "pk": {
            "S": "PROBLEM#23"
          },
          "sk": {
            "S": "CHOICE#91"
          },
          "id": {
            "N": "91"
          },
          "problem_id": {
            "N": "23"
          },
          "choice_text": {
            "S": "37"
          },
          "is_correct": {
            "BOOL": true
          }
        }
      }
    },
    {
      "PutRequest": {
        "Item": {
          "pk": {
            "S": "PROBLEM#23"
          },
          "sk": {
            "S": "CHOICE#92"
          },
          "id": {
            "N": "92"
          },
          "problem_id": {
            "N": "23"
          },
          "choice_text": {
            "S": "41"
          },
          "is_correct": {
            "BOOL": false
          }
        }
      }
    },
    {
      "PutRequest": {
        "Item": {
          "pk": {
            "S": "PROBLEM#24"
          },
          "sk": {
            "S": "CHOICE#93"
          },
          "id": {
            "N": "93"
          },
          "problem_id": {
            "N": "24"
          },
          "choice_text": {
            "S": "0.81"
          },
          "is_correct": {
            "BOOL": false
          }
        }
      }
    },
    {
      "PutRequest": {
        "Item": {
          "pk": {
            "S": "PROBLEM#24"
          },
          "sk": {
            "S": "CHOICE#94"
          },
          "id": {
            "N": "94"
          },
          "problem_id": {
            "N": "24"
          },
          "choice_text": {
            "S": "0.77"
          },
          "is_correct": {
            "BOOL": true
          }
        }
      }
    },
    {
      "PutRequest": {
        "Item": {
          "pk": {
            "S": "PROBLEM#24"
          },
          "sk": {
            "S": "CHOICE#95"
          },
          "id": {
            "N": "95"
          },
          "problem_id": {
            "N": "24"
          },
          "choice_text": {
            "S": "0.68"
          },
          "is_correct": {
            "BOOL": false
          }
        }
      }
    },
    {
      "PutRequest": {
        "Item": {
          "pk": {
            "S": "PROBLEM#24"
          },
          "sk": {
            "S": "CHOICE#96"
          },
          "id": {
            "N": "96"
          },
          "problem_id": {
            "N": "24"
          },
          "choice_text": {
            "S": "0.65"
          },
          "is_correct": {
            "BOOL": false
          }
        }
      }
    },
    {
      "PutRequest": {
        "Item": {
          "pk": {
            "S": "PROBLEM#25"
          },
          "sk": {
            "S": "CHOICE#97"
          },
          "id": {
            "N": "97"
          },
          "problem_id": {
            "N": "25"
          },
          "choice_text": {
            "S": "140"
          },
          "is_correct": {
            "BOOL": false
          }
        }
      }
    },
    {
      "PutRequest": {
        "Item": {
          "pk": {
            "S": "PROBLEM#25"
          },
          "sk": {
            "S": "CHOICE#98"
          },
          "id": {
            "N": "98"
          },
          "problem_id": {
            "N": "25"
          },
          "choice_text": {
            "S": "135"
          },
          "is_correct": {
            "BOOL": true
          }
        }
      }
    },
    {
      "PutRequest": {
        "Item": {
          "pk": {
            "S": "PROBLEM#25"
          },
          "sk": {
            "S": "CHOICE#99"
          },
          "id": {
            "N": "99"
          },
          "problem_id": {
            "N": "25"
          },
          "choice_text": {
            "S": "125"
          },
          "is_correct": {
            "BOOL": false
          }
        }
      }
    },
    {
      "PutRequest": {
        "Item": {
          "pk": {
            "S": "PROBLEM#25"
          },
          "sk": {
            "S": "CHOICE#100"
          },
          "id": {
            "N": "100"
          },
          "problem_id": {
            "N": "25"
          },
          "choice_text": {
            "S": "130"
          },
          "is_correct": {
            "BOOL": false
          }
        }
      }
    }
  ]
}